jenkins_testing_folder_df/__init__.py
jenkins_testing_folder_df/module.py
jenkins_job_tests_delete-0.1.3.dist-info/LICENSE
jenkins_job_tests_delete-0.1.3.dist-info/METADATA
jenkins_job_tests_delete-0.1.3.dist-info/WHEEL
jenkins_job_tests_delete-0.1.3.dist-info/top_level.txt
jenkins_job_tests_delete-0.1.3.dist-info/RECORD
